{
  "providers": {
    "awscloudformation": {
      "AuthRoleName": "amplify-awsomenlp-transdev-145032-authRole",
      "UnauthRoleArn": "arn:aws:iam::755811905719:role/amplify-awsomenlp-transdev-145032-unauthRole",
      "AuthRoleArn": "arn:aws:iam::755811905719:role/amplify-awsomenlp-transdev-145032-authRole",
      "Region": "eu-west-1",
      "DeploymentBucketName": "amplify-awsomenlp-transdev-145032-deployment",
      "UnauthRoleName": "amplify-awsomenlp-transdev-145032-unauthRole",
      "StackName": "amplify-awsomenlp-transdev-145032",
      "StackId": "arn:aws:cloudformation:eu-west-1:755811905719:stack/amplify-awsomenlp-transdev-145032/7b32a1a0-0930-11ee-be4b-02c2c4e76eaf",
      "AmplifyAppId": "dwapbqykinfdb"
    }
  },
  "api": {
    "awsomenlp": {
      "dependsOn": [],
      "output": {
        "authConfig": {
          "additionalAuthenticationProviders": [],
          "defaultAuthentication": {
            "apiKeyConfig": {
              "apiKeyExpirationDays": 7
            },
            "authenticationType": "API_KEY"
          }
        },
        "GraphQLAPIIdOutput": "dz4g5mhw3vgzhkuzr4vgrjqzuq",
        "GraphQLAPIEndpointOutput": "https://uia6ytrhmjat5l2zgndggu5sfa.appsync-api.eu-west-1.amazonaws.com/graphql",
        "GraphQLAPIKeyOutput": "da2-o6vkouxdrvfl5eyfngamgjkbju"
      },
      "providerPlugin": "awscloudformation",
      "service": "AppSync",
      "lastPushTimeStamp": "2023-06-14T11:44:24.743Z",
      "providerMetadata": {
        "s3TemplateURL": "https://s3.amazonaws.com/amplify-awsomenlp-transdev-145032-deployment/amplify-cfn-templates/api/cloudformation-template.json",
        "logicalId": "apiawsomenlp"
      },
      "lastPushDirHash": "mdalov68MqEbNcLg8C5iQ6Q464w="
    }
  },
  "function": {
    "UserConfigFunction": {
      "build": true,
      "providerPlugin": "awscloudformation",
      "service": "Lambda",
      "output": {
        "LambdaExecutionRoleArn": "arn:aws:iam::755811905719:role/awsomenlpLambdaRolee754d004-transdev",
        "Region": "eu-west-1",
        "Arn": "arn:aws:lambda:eu-west-1:755811905719:function:UserConfigFunction-transdev",
        "Name": "UserConfigFunction-transdev",
        "LambdaExecutionRole": "awsomenlpLambdaRolee754d004-transdev"
      },
      "lastPushTimeStamp": "2023-06-14T11:44:24.758Z",
      "providerMetadata": {
        "s3TemplateURL": "https://s3.amazonaws.com/amplify-awsomenlp-transdev-145032-deployment/amplify-cfn-templates/function/UserConfigFunction-cloudformation-template.json",
        "logicalId": "functionUserConfigFunction"
      },
      "lastBuildTimeStamp": "2023-06-14T10:23:22.349Z",
      "lastBuildType": "PROD",
      "lastPackageTimeStamp": "2023-06-14T10:23:22.545Z",
      "distZipFilename": "UserConfigFunction-30396c50793166426d54-build.zip",
      "s3Bucket": {
        "deploymentBucketName": "amplify-awsomenlp-transdev-145032-deployment",
        "s3Key": "amplify-builds/UserConfigFunction-30396c50793166426d54-build.zip"
      },
      "lastPushDirHash": "3q3dyAFG3pDlBtNHVrX4CkXWg3M="
    },
    "checkingUrl": {
      "build": true,
      "providerPlugin": "awscloudformation",
      "service": "Lambda",
      "output": {
        "LambdaExecutionRoleArn": "arn:aws:iam::755811905719:role/awsomenlpLambdaRole19b815c5-transdev",
        "Region": "eu-west-1",
        "Arn": "arn:aws:lambda:eu-west-1:755811905719:function:checkingUrl-transdev",
        "Name": "checkingUrl-transdev",
        "LambdaExecutionRole": "awsomenlpLambdaRole19b815c5-transdev"
      },
      "lastPushTimeStamp": "2023-06-14T11:44:24.772Z",
      "providerMetadata": {
        "s3TemplateURL": "https://s3.amazonaws.com/amplify-awsomenlp-transdev-145032-deployment/amplify-cfn-templates/function/checkingUrl-cloudformation-template.json",
        "logicalId": "functioncheckingUrl"
      },
      "lastBuildTimeStamp": "2023-06-14T10:23:22.359Z",
      "lastBuildType": "PROD",
      "lastPackageTimeStamp": "2023-06-14T10:23:22.475Z",
      "distZipFilename": "checkingUrl-49754e4348775a2b586e-build.zip",
      "s3Bucket": {
        "deploymentBucketName": "amplify-awsomenlp-transdev-145032-deployment",
        "s3Key": "amplify-builds/checkingUrl-49754e4348775a2b586e-build.zip"
      },
      "lastPushDirHash": "5Mo7+/Pq6zWvi1n8pbBDsjxfrdQ="
    },
    "getBlogContent": {
      "build": true,
      "providerPlugin": "awscloudformation",
      "service": "Lambda",
      "output": {
        "LambdaExecutionRoleArn": "arn:aws:iam::755811905719:role/awsomenlpLambdaRole4c31b8f7-transdev",
        "Region": "eu-west-1",
        "Arn": "arn:aws:lambda:eu-west-1:755811905719:function:getBlogContent-transdev",
        "Name": "getBlogContent-transdev",
        "LambdaExecutionRole": "awsomenlpLambdaRole4c31b8f7-transdev"
      },
      "lastPushTimeStamp": "2023-06-14T11:44:24.785Z",
      "providerMetadata": {
        "s3TemplateURL": "https://s3.amazonaws.com/amplify-awsomenlp-transdev-145032-deployment/amplify-cfn-templates/function/getBlogContent-cloudformation-template.json",
        "logicalId": "functiongetBlogContent"
      },
      "s3Bucket": {
        "deploymentBucketName": "amplify-awsomenlp-transdev-145032-deployment",
        "s3Key": "amplify-builds/getBlogContent-696a5656524d66537936-build.zip"
      },
      "lastBuildTimeStamp": "2023-06-14T10:23:25.186Z",
      "lastBuildType": "PROD",
      "lastPackageTimeStamp": "2023-06-14T10:23:28.010Z",
      "distZipFilename": "getBlogContent-696a5656524d66537936-build.zip",
      "lastPushDirHash": "vcSmE4iCpFz2OGJd+u3MzEmw8Rk="
    },
    "stepFunctionInvoker": {
      "build": true,
      "providerPlugin": "awscloudformation",
      "service": "Lambda",
      "lastBuildTimeStamp": "2023-06-14T11:42:33.583Z",
      "lastBuildType": "PROD",
      "lastPackageTimeStamp": "2023-06-14T11:42:35.650Z",
      "distZipFilename": "stepFunctionInvoker-41684756544473507072-build.zip",
      "s3Bucket": {
        "deploymentBucketName": "amplify-awsomenlp-transdev-145032-deployment",
        "s3Key": "amplify-builds/stepFunctionInvoker-41684756544473507072-build.zip"
      },
      "providerMetadata": {
        "s3TemplateURL": "https://s3.amazonaws.com/amplify-awsomenlp-transdev-145032-deployment/amplify-cfn-templates/function/stepFunctionInvoker-cloudformation-template.json",
        "logicalId": "functionstepFunctionInvoker"
      },
      "lastPushTimeStamp": "2023-06-14T11:44:24.801Z",
      "output": {
        "LambdaExecutionRoleArn": "arn:aws:iam::755811905719:role/awsomenlpLambdaRole42be966f-transdev",
        "Region": "eu-west-1",
        "Arn": "arn:aws:lambda:eu-west-1:755811905719:function:stepFunctionInvoker-transdev",
        "Name": "stepFunctionInvoker-transdev",
        "LambdaExecutionRole": "awsomenlpLambdaRole42be966f-transdev"
      },
      "lastPushDirHash": "AhGVTDsPprC5yxc1obv5VC8VS+Y="
    }
  },
  "storage": {}
}